timestamps/__init__.py
timestamps/__main__.py
timestamps-1.3.0.dist-info/METADATA
timestamps-1.3.0.dist-info/RECORD
timestamps-1.3.0.dist-info/WHEEL
timestamps-1.3.0.dist-info/top_level.txt
