Metadata-Version: 2.1
Name: timestamps
Version: 1.3.0
Summary: Timestamp manager
Home-page: https://github.com/gndu91/timestamps
Author: GHOUL Nadir
Author-email: gndu91@gmail.com
License: UNKNOWN
Platform: UNKNOWN
Classifier: Programming Language :: Python :: 3
Classifier: License :: OSI Approved :: MIT License
Classifier: Operating System :: OS Independent
